declareq/__about__.py
declareq/__init__.py
declareq/annotations.py
declareq/arguments.py
declareq/builder.py
declareq/commands.py
declareq/exceptions.py
declareq/interfaces.py
declareq/request.py
declareq/utils.py
declareq-0.1.10.dist-info/LICENSE
declareq-0.1.10.dist-info/METADATA
declareq-0.1.10.dist-info/WHEEL
declareq-0.1.10.dist-info/top_level.txt
declareq-0.1.10.dist-info/RECORD
