Metadata-Version: 2.1
Name: declareq
Version: 0.1.10
Summary: declare http request over requests
Home-page: https://github.com/wangxiaochuang/declareq
Author: wangxiaochuang
Author-email: jackstrawxiaoxin@gmail.com
License: MIT
Classifier: License :: OSI Approved :: MIT License
Classifier: Programming Language :: Python
Classifier: Programming Language :: Python :: 3
Classifier: Programming Language :: Python :: 3.6
Classifier: Programming Language :: Python :: Implementation :: CPython
Classifier: Programming Language :: Python :: Implementation :: PyPy
Requires-Python: >=3.6.0
License-File: LICENSE
Requires-Dist: requests
Requires-Dist: retrying
Requires-Dist: uritemplate
Requires-Dist: toolz
Requires-Dist: foxmock
Provides-Extra: tests
Requires-Dist: pytest ; extra == 'tests'
